bdownload/VERSION
bdownload/__init__.py
bdownload/__main__.py
bdownload/cli.py
bdownload/download.py
bdownload-0.1.4.dist-info/METADATA
bdownload-0.1.4.dist-info/WHEEL
bdownload-0.1.4.dist-info/entry_points.txt
bdownload-0.1.4.dist-info/top_level.txt
bdownload-0.1.4.dist-info/RECORD
