Metadata-Version: 2.1
Name: bdownload
Version: 0.1.4
Summary: A multi-threaded and multi-source aria2-like batch file downloading library for Python
Home-page: https://github.com/Jesseatgao/bdownload
Author: Jesse Gao
Author-email: changxigao@gmail.com
License: MIT License
Platform: UNKNOWN
Classifier: Intended Audience :: Developers
Classifier: Environment :: Console
Classifier: Programming Language :: Python
Classifier: Programming Language :: Python :: 2
Classifier: Programming Language :: Python :: 2.7
Classifier: Programming Language :: Python :: 3
Classifier: Programming Language :: Python :: 3.6
Classifier: Programming Language :: Python :: 3.7
Classifier: Programming Language :: Python :: 3.8
Classifier: Programming Language :: Python :: 3.9
Classifier: Programming Language :: Python :: Implementation :: CPython
Classifier: Programming Language :: Python :: Implementation :: PyPy
Classifier: License :: OSI Approved :: MIT License
Classifier: Operating System :: OS Independent
Requires-Python: >=2.7, !=3.0.*, !=3.1.*, !=3.2.*, !=3.3.*, !=3.4.*, !=3.5.*
Requires-Dist: requests[socks]
Requires-Dist: requests
Requires-Dist: clint
Requires-Dist: sphinx
Requires-Dist: futures ; python_version == "2.7"
Requires-Dist: Jinja2 (==2.11.3) ; python_version == "3.6"
